{
  "address": "0x4CF488387F035FF08c371515562CBa712f9015d4",
  "symbol": "WPR",
  "decimals": "18",
  "token": "WePower",
  "description": "WePower is a blockchain-based green energy financing and trading platform. It connects energy buyers directly with the green energy producers and creates an opportunity to purchase energy upfront at below market rates. WePower uses Smart Energy Contracts to standardize, simplify and open globally the currently existing energy investment ecosystem. Smart Energy Contracts ensures liquidity and extends access to capital. Moreover, it provides the first access to live trade in renewable energy globally for everyone.",
  "logo": "https://image.ibb.co/dzfCXJ/Wepower_logo_256x256.png",
  "discussions": "https://t.me/WePowerNetwork",
  "website": "https://wepower.network/"
}
